{
    "pr_account": "patient/Account.read",
    "pr_allergyintolerance": "patient/AllergyIntolerance.read",
    "pr_appointment": "patient/Appointment.read",
    "pr_binary": "patient/Binary.read",
    "pr_careplan": "patient/CarePlan.read",
    "pr_careteam": "patient/CareTeam.read",
    "pr_chargeitem": "patient/ChargeItem.read",
    "pr_communication": "patient/Communication.read",
    "pr_condition": "patient/Condition.read",
    "pr_consent": "patient/Consent.read",
    "pr_coverage": "patient/Coverage.read",
    "pr_device": "patient/Device.read",
    "pr_documentreference": "patient/DocumentReference.read",
    "pr_encounter": "patient/Encounter.read",
    "pr_familymemberhistory": "patient/FamilyMemberHistory.read",
    "pr_goal": "patient/Goal.read",
    "pr_immunization": "patient/Immunization.read",
    "pr_medicationrequest": "patient/MedicationRequest.read",
    "pr_nutritionorder": "patient/NutritionOrder.read",
    "pr_observation": "patient/Observation.read",
    "pr_patient": "patient/Patient.read",
    "pr_person": "patient/Person.read",
    "pr_procedure": "patient/Procedure.read",
    "pr_provenance": "patient/Provenance.read",
    "pr_questionnaire": "patient/Questionnaire.read",
    "pr_questionnaireresponse": "patient/QuestionnaireResponse.read",
    "pr_relatedperson": "patient/RelatedPerson.read",
    "pr_schedule": "patient/Schedule.read",
    "pr_servicerequest": "patient/ServiceRequest.read",
    "pr_slot": "patient/Slot.read",
    "pw_allergyintolerance": "patient/AllergyIntolerance.write",
    "pw_appointment": "patient/Appointment.write",
    "pw_basic": "patient/Basic.write",
    "pw_binary": "patient/Binary.write",
    "pw_communication": "patient/Communication.write",
    "pw_condition": "patient/Condition.write",
    "pw_coverage": "patient/Coverage.write",
    "pw_documentreference": "patient/DocumentReference.write",
    "pw_encounter": "patient/Encounter.write",
    "pw_familymemberhistory": "patient/FamilyMemberHistory.write",
    "pw_immunization": "patient/Immunization.write",
    "pw_medicationrequest": "patient/MedicationRequest.write",
    "pw_observation": "patient/Observation.write",
    "pw_patient": "patient/Patient.write",
    "pw_procedure": "patient/Procedure.write",
    "pw_provenance": "patient/Provenance.write",
    "pw_questionnaireresponse": "patient/QuestionnaireResponse.write",
    "pw_relatedperson": "patient/RelatedPerson.write",
    "pw_slot": "patient/Slot.write",
    "ur_account": "user/Account.read",
    "ur_allergyintolerance": "user/AllergyIntolerance.read",
    "ur_appointment": "user/Appointment.read",
    "ur_binary": "user/Binary.read",
    "ur_careplan": "user/CarePlan.read",
    "ur_careteam": "user/CareTeam.read",
    "ur_chargeitem": "user/ChargeItem.read",
    "ur_communication": "user/Communication.read",
    "ur_condition": "user/Condition.read",
    "ur_consent": "user/Consent.read",
    "ur_coverage": "user/Coverage.read",
    "ur_device": "user/Device.read",
    "ur_documentreference": "user/DocumentReference.read",
    "ur_encounter": "user/Encounter.read",
    "ur_familymemberhistory": "user/FamilyMemberHistory.read",
    "ur_goal": "user/Goal.read",
    "ur_immunization": "user/Immunization.read",
    "ur_location": "user/Location.read",
    "ur_medicationrequest": "user/MedicationRequest.read",
    "ur_nutritionorder": "user/NutritionOrder.read",
    "ur_observation": "user/Observation.read",
    "ur_organization": "user/Organization.read",
    "ur_patient": "user/Patient.read",
    "ur_person": "user/Person.read",
    "ur_practitioner": "user/Practitioner.read",
    "ur_procedure": "user/Procedure.read",
    "ur_provenance": "user/Provenance.read",
    "ur_questionnaire": "user/Questionnaire.read",
    "ur_questionnaireresponse": "user/QuestionnaireResponse.read",
    "ur_relatedperson": "user/RelatedPerson.read",
    "ur_schedule": "user/Schedule.read",
    "ur_servicerequest": "user/ServiceRequest.read",
    "ur_slot": "user/Slot.read",
    "uw_allergyintolerance": "user/AllergyIntolerance.write",
    "uw_appointment": "user/Appointment.write",
    "uw_binary": "user/Binary.write",
    "uw_basic": "user/Basic.write",
    "uw_communication": "user/Communication.write",
    "uw_condition": "user/Condition.write",
    "uw_coverage": "user/Coverage.write",
    "uw_documentreference": "user/DocumentReference.write",
    "uw_encounter": "user/Encounter.write",
    "uw_familymemberhistory": "user/FamilyMemberHistory.write",
    "uw_immunization": "user/Immunization.write",
    "uw_medicationrequest": "user/MedicationRequest.write",
    "uw_observation": "user/Observation.write",
    "uw_organization": "user/Organization.write",
    "uw_patient": "user/Patient.write",
    "uw_practitioner": "user/Practitioner.write",
    "uw_procedure": "user/Procedure.write",
    "uw_provenance": "user/Provenance.write",
    "uw_questionnaireresponse": "user/QuestionnaireResponse.write",
    "uw_relatedperson": "user/RelatedPerson.write",
    "uw_slot": "user/Slot.write"
}
